yaml_builder/__init__.py
yaml_builder/loader.py
yaml_builder-0.1.1.dist-info/DESCRIPTION.rst
yaml_builder-0.1.1.dist-info/METADATA
yaml_builder-0.1.1.dist-info/RECORD
yaml_builder-0.1.1.dist-info/WHEEL
yaml_builder-0.1.1.dist-info/entry_points.txt
yaml_builder-0.1.1.dist-info/metadata.json
yaml_builder-0.1.1.dist-info/top_level.txt
