Metadata-Version: 2.0
Name: yaml-builder
Version: 0.1.1
Summary: A wrapper around PyYaml for building complex yaml files
Home-page: https://github.com/spockNinja/py-yaml-builder
Author: Jacob Foster
Author-email: UNKNOWN
License: UNKNOWN
Keywords: yaml compose build cloudformation tool
Platform: UNKNOWN
Classifier: Development Status :: 4 - Beta
Classifier: Intended Audience :: Developers
Classifier: Topic :: Software Development :: Build Tools
Classifier: License :: OSI Approved :: MIT License
Classifier: Programming Language :: Python :: 2
Classifier: Programming Language :: Python :: 2.7
Classifier: Programming Language :: Python :: 3
Classifier: Programming Language :: Python :: 3.4
Classifier: Programming Language :: Python :: 3.5
Classifier: Programming Language :: Python :: 3.6
Requires-Dist: PyYAML
